setup.py
pshello/__init__.py
pshello.egg-info/PKG-INFO
pshello.egg-info/SOURCES.txt
pshello.egg-info/dependency_links.txt
pshello.egg-info/not-zip-safe
pshello.egg-info/top_level.txt