Metadata-Version: 1.0
Name: pshello
Version: 0.1
Summary: The funniest joke in the world
Home-page: http://github.com/storborg/funniest
Author: Prathamesh Sawant
Author-email: prathamesh.sawant@varaunited.in
License: ICICI
Platform: UNKNOWN
